sos_rmarkdown/__init__.py
sos_rmarkdown/_version.py
sos_rmarkdown/converter.py
sos_rmarkdown-0.1.4.dist-info/LICENSE
sos_rmarkdown-0.1.4.dist-info/METADATA
sos_rmarkdown-0.1.4.dist-info/WHEEL
sos_rmarkdown-0.1.4.dist-info/entry_points.txt
sos_rmarkdown-0.1.4.dist-info/top_level.txt
sos_rmarkdown-0.1.4.dist-info/RECORD
