Metadata-Version: 2.1
Name: sos-rmarkdown
Version: 0.1.4
Summary: A Rmarkdown to SoS Notebook converter
Home-page: https://github.com/vatlab/sos-rmarkdown
Author: Bo Peng
Author-email: bpeng@mdanderson.org
Maintainer: Bo Peng
Maintainer-email: bpeng@mdanderson.org
License: 3-clause BSD
Platform: UNKNOWN
Classifier: Development Status :: 4 - Beta
Classifier: Environment :: Console
Classifier: License :: OSI Approved :: BSD License
Classifier: Natural Language :: English
Classifier: Operating System :: POSIX :: Linux
Classifier: Operating System :: MacOS :: MacOS X
Classifier: Operating System :: Microsoft :: Windows
Classifier: Intended Audience :: Information Technology
Classifier: Intended Audience :: Science/Research
Classifier: Programming Language :: Python :: 3 :: Only
Classifier: Programming Language :: Python :: 3.6
Classifier: Programming Language :: Python :: Implementation :: CPython
Requires-Python: >=3.6
Requires-Dist: sos (>=0.20.9)
Requires-Dist: sos-notebook (>=0.20.9)
Requires-Dist: sos-r
Requires-Dist: markdown-kernel
Requires-Dist: papermill
Requires-Dist: sos-papermill
Requires-Dist: nbformat
Requires-Dist: nbconvert (>=5.1.1)
